{
  "group.nd.name": "2PM 준케이",
  "query": "(2PM 준케이 OR 준케이 2PM OR 준케이 투피엠 OR 투피엠 준케이) lang:ko -is:retweet -is:nullcast",
  "collab_start_week": "2025-W37",
  "collab_start_date": "2025-09-08",
  "window_start": "2025-03-08T00:00:00Z",
  "window_end": "2025-07-08T00:00:00Z",
  "weekly_counts": {
    "2025-W23": 42,
    "2025-W24": 78,
    "2025-W25": 58,
    "2025-W26": 44,
    "2025-W27": 43,
    "2025-W28": 12,
    "2025-W19": 67,
    "2025-W20": 79,
    "2025-W21": 54,
    "2025-W22": 62,
    "2025-W14": 57,
    "2025-W15": 64,
    "2025-W16": 26,
    "2025-W17": 34,
    "2025-W18": 39,
    "2025-W10": 2,
    "2025-W11": 23,
    "2025-W12": 23,
    "2025-W13": 17
  },
  "lag_features": {
    "count_lag_9w": 12,
    "count_lag_10w": 43,
    "count_lag_11w": 44,
    "count_lag_12w": 58,
    "count_lag_13w": 78,
    "count_lag_14w": 42,
    "count_lag_15w": 62,
    "count_lag_16w": 54,
    "count_lag_17w": 79,
    "count_lag_18w": 67,
    "count_lag_19w": 39,
    "count_lag_20w": 34,
    "count_lag_21w": 26,
    "count_lag_22w": 64,
    "count_lag_23w": 57,
    "count_lag_24w": 17,
    "count_lag_25w": 23,
    "count_lag_26w": 23
  },
  "total_count_2to6m": 822,
  "rate_limit": {
    "limit": "300",
    "remaining": "272",
    "reset": "1772207198"
  },
  "saved_at_utc": "2026-02-27T15:33:54Z"
}