{
  "group.nd.name": "BAE173 한결",
  "query": "(BAE173 한결 OR 비에이이173 한결 OR 한결 BAE173 OR 한결 비에이이173) lang:ko -is:retweet -is:nullcast",
  "collab_start_week": "2024-W10",
  "collab_start_date": "2024-03-04",
  "window_start": "2023-09-04T00:00:00Z",
  "window_end": "2024-01-04T00:00:00Z",
  "weekly_counts": {
    "2023-W49": 19,
    "2023-W50": 15,
    "2023-W51": 11,
    "2023-W52": 12,
    "2024-W01": 2,
    "2023-W44": 4,
    "2023-W45": 17,
    "2023-W46": 14,
    "2023-W47": 13,
    "2023-W48": 4,
    "2023-W40": 6,
    "2023-W41": 1,
    "2023-W42": 13,
    "2023-W43": 5,
    "2023-W36": 36,
    "2023-W37": 101,
    "2023-W38": 18,
    "2023-W39": 17
  },
  "lag_features": {
    "count_lag_9w": 2,
    "count_lag_10w": 12,
    "count_lag_11w": 11,
    "count_lag_12w": 15,
    "count_lag_13w": 19,
    "count_lag_14w": 4,
    "count_lag_15w": 13,
    "count_lag_16w": 14,
    "count_lag_17w": 17,
    "count_lag_18w": 4,
    "count_lag_19w": 5,
    "count_lag_20w": 13,
    "count_lag_21w": 1,
    "count_lag_22w": 6,
    "count_lag_23w": 17,
    "count_lag_24w": 18,
    "count_lag_25w": 101,
    "count_lag_26w": 36
  },
  "total_count_2to6m": 308,
  "rate_limit": {
    "limit": "300",
    "remaining": "224",
    "reset": "1772208181"
  },
  "saved_at_utc": "2026-02-27T15:49:15Z"
}