{
  "group.nd.name": "더보이즈 제이콥",
  "query": "(THE BOYZ 제이콥 OR 더보이즈 제이콥 OR 제이콥 THE BOYZ OR 제이콥 더보이즈) lang:ko -is:retweet -is:nullcast",
  "collab_start_week": "2025-W21",
  "collab_start_date": "2025-05-19",
  "window_start": "2024-11-19T00:00:00Z",
  "window_end": "2025-03-19T00:00:00Z",
  "weekly_counts": {
    "2025-W07": 561,
    "2025-W08": 567,
    "2025-W09": 752,
    "2025-W10": 732,
    "2025-W11": 490,
    "2025-W12": 157,
    "2025-W03": 557,
    "2025-W04": 416,
    "2025-W05": 1127,
    "2025-W06": 1087,
    "2024-W51": 352,
    "2024-W52": 387,
    "2025-W01": 330,
    "2025-W02": 377,
    "2024-W47": 567,
    "2024-W48": 423,
    "2024-W49": 443,
    "2024-W50": 392
  },
  "lag_features": {
    "count_lag_9w": 157,
    "count_lag_10w": 490,
    "count_lag_11w": 732,
    "count_lag_12w": 752,
    "count_lag_13w": 567,
    "count_lag_14w": 561,
    "count_lag_15w": 1087,
    "count_lag_16w": 1127,
    "count_lag_17w": 416,
    "count_lag_18w": 557,
    "count_lag_19w": 377,
    "count_lag_20w": 330,
    "count_lag_21w": 387,
    "count_lag_22w": 352,
    "count_lag_23w": 392,
    "count_lag_24w": 443,
    "count_lag_25w": 423,
    "count_lag_26w": 567
  },
  "total_count_2to6m": 9717,
  "rate_limit": {
    "limit": "300",
    "remaining": "167",
    "reset": "1772232197"
  },
  "saved_at_utc": "2026-02-27T22:30:47Z"
}