{
  "group.nd.name": "데이식스 성진",
  "query": "(DAY6 성진 OR 데이식스 성진 OR 성진 DAY6 OR 성진 데이식스) lang:ko -is:retweet -is:nullcast",
  "collab_start_week": "2025-W19",
  "collab_start_date": "2025-05-05",
  "window_start": "2024-11-05T00:00:00Z",
  "window_end": "2025-03-05T00:00:00Z",
  "weekly_counts": {
    "2025-W05": 758,
    "2025-W06": 541,
    "2025-W07": 720,
    "2025-W08": 484,
    "2025-W09": 477,
    "2025-W10": 306,
    "2025-W01": 529,
    "2025-W02": 462,
    "2025-W03": 523,
    "2025-W04": 419,
    "2024-W49": 649,
    "2024-W50": 634,
    "2024-W51": 1308,
    "2024-W52": 514,
    "2024-W45": 1574,
    "2024-W46": 970,
    "2024-W47": 938,
    "2024-W48": 860
  },
  "lag_features": {
    "count_lag_9w": 306,
    "count_lag_10w": 477,
    "count_lag_11w": 484,
    "count_lag_12w": 720,
    "count_lag_13w": 541,
    "count_lag_14w": 758,
    "count_lag_15w": 419,
    "count_lag_16w": 523,
    "count_lag_17w": 462,
    "count_lag_18w": 529,
    "count_lag_19w": 514,
    "count_lag_20w": 1308,
    "count_lag_21w": 634,
    "count_lag_22w": 649,
    "count_lag_23w": 860,
    "count_lag_24w": 938,
    "count_lag_25w": 970,
    "count_lag_26w": 1574
  },
  "total_count_2to6m": 12666,
  "rate_limit": {
    "limit": "300",
    "remaining": "23",
    "reset": "1772232197"
  },
  "saved_at_utc": "2026-02-27T22:33:15Z"
}