{
  "group.nd.name": "드리핀 차준호",
  "query": "(DRIPPIN 차준호 OR 드리핀 차준호 OR 차준호 DRIPPIN OR 차준호 드리핀) lang:ko -is:retweet -is:nullcast",
  "collab_start_week": "2024-W32",
  "collab_start_date": "2024-08-05",
  "window_start": "2024-02-05T00:00:00Z",
  "window_end": "2024-06-05T00:00:00Z",
  "weekly_counts": {
    "2024-W18": 83,
    "2024-W19": 113,
    "2024-W20": 97,
    "2024-W21": 70,
    "2024-W22": 40,
    "2024-W23": 10,
    "2024-W14": 190,
    "2024-W15": 145,
    "2024-W16": 116,
    "2024-W17": 188,
    "2024-W10": 51,
    "2024-W11": 59,
    "2024-W12": 13,
    "2024-W13": 33,
    "2024-W06": 24,
    "2024-W07": 38,
    "2024-W08": 11,
    "2024-W09": 11
  },
  "lag_features": {
    "count_lag_9w": 10,
    "count_lag_10w": 40,
    "count_lag_11w": 70,
    "count_lag_12w": 97,
    "count_lag_13w": 113,
    "count_lag_14w": 83,
    "count_lag_15w": 188,
    "count_lag_16w": 116,
    "count_lag_17w": 145,
    "count_lag_18w": 190,
    "count_lag_19w": 33,
    "count_lag_20w": 13,
    "count_lag_21w": 59,
    "count_lag_22w": 51,
    "count_lag_23w": 11,
    "count_lag_24w": 11,
    "count_lag_25w": 38,
    "count_lag_26w": 24
  },
  "total_count_2to6m": 1292,
  "rate_limit": {
    "limit": "300",
    "remaining": "228",
    "reset": "1772243345"
  },
  "saved_at_utc": "2026-02-28T01:34:57Z"
}