{
  "group.nd.name": "미야오 안나",
  "query": "(미야오 안나 OR 안나 미야오) lang:ko -is:retweet -is:nullcast",
  "collab_start_week": "2025-W41",
  "collab_start_date": "2025-10-06",
  "window_start": "2025-04-06T00:00:00Z",
  "window_end": "2025-08-06T00:00:00Z",
  "weekly_counts": {
    "2025-W27": 163,
    "2025-W28": 73,
    "2025-W29": 61,
    "2025-W30": 131,
    "2025-W31": 216,
    "2025-W32": 63,
    "2025-W23": 124,
    "2025-W24": 129,
    "2025-W25": 74,
    "2025-W26": 101,
    "2025-W19": 192,
    "2025-W20": 392,
    "2025-W21": 158,
    "2025-W22": 148,
    "2025-W14": 9,
    "2025-W15": 21,
    "2025-W16": 50,
    "2025-W17": 55,
    "2025-W18": 285
  },
  "lag_features": {
    "count_lag_9w": 63,
    "count_lag_10w": 216,
    "count_lag_11w": 131,
    "count_lag_12w": 61,
    "count_lag_13w": 73,
    "count_lag_14w": 163,
    "count_lag_15w": 101,
    "count_lag_16w": 74,
    "count_lag_17w": 129,
    "count_lag_18w": 124,
    "count_lag_19w": 148,
    "count_lag_20w": 158,
    "count_lag_21w": 392,
    "count_lag_22w": 192,
    "count_lag_23w": 285,
    "count_lag_24w": 55,
    "count_lag_25w": 50,
    "count_lag_26w": 21
  },
  "total_count_2to6m": 2436,
  "rate_limit": {
    "limit": "300",
    "remaining": "188",
    "reset": "1772247497"
  },
  "saved_at_utc": "2026-02-28T02:44:50Z"
}