{
  "group.nd.name": "박규리",
  "query": "박규리 lang:ko -is:retweet -is:nullcast",
  "collab_start_week": "2025-W36",
  "collab_start_date": "2025-09-01",
  "window_start": "2025-03-01T00:00:00Z",
  "window_end": "2025-07-01T00:00:00Z",
  "weekly_counts": {
    "2025-W22": 53,
    "2025-W23": 93,
    "2025-W24": 61,
    "2025-W25": 47,
    "2025-W26": 65,
    "2025-W27": 32,
    "2025-W18": 54,
    "2025-W19": 49,
    "2025-W20": 169,
    "2025-W21": 177,
    "2025-W13": 57,
    "2025-W14": 61,
    "2025-W15": 104,
    "2025-W16": 53,
    "2025-W17": 72,
    "2025-W09": 3,
    "2025-W10": 33,
    "2025-W11": 41,
    "2025-W12": 21
  },
  "lag_features": {
    "count_lag_9w": 32,
    "count_lag_10w": 65,
    "count_lag_11w": 47,
    "count_lag_12w": 61,
    "count_lag_13w": 93,
    "count_lag_14w": 53,
    "count_lag_15w": 177,
    "count_lag_16w": 169,
    "count_lag_17w": 49,
    "count_lag_18w": 54,
    "count_lag_19w": 72,
    "count_lag_20w": 53,
    "count_lag_21w": 104,
    "count_lag_22w": 61,
    "count_lag_23w": 57,
    "count_lag_24w": 21,
    "count_lag_25w": 41,
    "count_lag_26w": 33
  },
  "total_count_2to6m": 1242,
  "rate_limit": {
    "limit": "300",
    "remaining": "164",
    "reset": "1772247497"
  },
  "saved_at_utc": "2026-02-28T02:45:11Z"
}