{
  "group.nd.name": "아이브 안유진",
  "query": "(IVE 안유진 OR 아이브 안유진 OR 안유진 IVE OR 안유진 아이브) lang:ko -is:retweet -is:nullcast",
  "collab_start_week": "2024-W09",
  "collab_start_date": "2024-02-26",
  "window_start": "2023-08-26T00:00:00Z",
  "window_end": "2023-12-26T00:00:00Z",
  "weekly_counts": {
    "2023-W47": 1083,
    "2023-W48": 1159,
    "2023-W49": 909,
    "2023-W50": 826,
    "2023-W51": 876,
    "2023-W52": 212,
    "2023-W43": 1501,
    "2023-W44": 870,
    "2023-W45": 992,
    "2023-W46": 650,
    "2023-W38": 1233,
    "2023-W39": 745,
    "2023-W40": 1356,
    "2023-W41": 1754,
    "2023-W42": 1506,
    "2023-W34": 173,
    "2023-W35": 931,
    "2023-W36": 727,
    "2023-W37": 1155
  },
  "lag_features": {
    "count_lag_9w": 212,
    "count_lag_10w": 876,
    "count_lag_11w": 826,
    "count_lag_12w": 909,
    "count_lag_13w": 1159,
    "count_lag_14w": 1083,
    "count_lag_15w": 650,
    "count_lag_16w": 992,
    "count_lag_17w": 870,
    "count_lag_18w": 1501,
    "count_lag_19w": 1506,
    "count_lag_20w": 1754,
    "count_lag_21w": 1356,
    "count_lag_22w": 745,
    "count_lag_23w": 1233,
    "count_lag_24w": 1155,
    "count_lag_25w": 727,
    "count_lag_26w": 931
  },
  "total_count_2to6m": 18485,
  "rate_limit": {
    "limit": "300",
    "remaining": "142",
    "reset": "1772257930"
  },
  "saved_at_utc": "2026-02-28T05:39:47Z"
}