{
  "group.nd.name": "에잇턴 윤규",
  "query": "(8TURN 윤규 OR 에잇턴 윤규 OR 윤규 8TURN OR 윤규 에잇턴) lang:ko -is:retweet -is:nullcast",
  "collab_start_week": "2023-W52",
  "collab_start_date": "2023-12-25",
  "window_start": "2023-06-25T00:00:00Z",
  "window_end": "2023-10-25T00:00:00Z",
  "weekly_counts": {
    "2023-W38": 27,
    "2023-W39": 30,
    "2023-W40": 46,
    "2023-W41": 28,
    "2023-W42": 41,
    "2023-W43": 23,
    "2023-W34": 58,
    "2023-W35": 35,
    "2023-W36": 101,
    "2023-W37": 34,
    "2023-W30": 47,
    "2023-W31": 33,
    "2023-W32": 54,
    "2023-W33": 53,
    "2023-W25": 1,
    "2023-W26": 179,
    "2023-W27": 120,
    "2023-W28": 81,
    "2023-W29": 89
  },
  "lag_features": {
    "count_lag_9w": 23,
    "count_lag_10w": 41,
    "count_lag_11w": 28,
    "count_lag_12w": 46,
    "count_lag_13w": 30,
    "count_lag_14w": 27,
    "count_lag_15w": 34,
    "count_lag_16w": 101,
    "count_lag_17w": 35,
    "count_lag_18w": 58,
    "count_lag_19w": 53,
    "count_lag_20w": 54,
    "count_lag_21w": 33,
    "count_lag_22w": 47,
    "count_lag_23w": 89,
    "count_lag_24w": 81,
    "count_lag_25w": 120,
    "count_lag_26w": 179
  },
  "total_count_2to6m": 1079,
  "rate_limit": {
    "limit": "300",
    "remaining": "43",
    "reset": "1772261511"
  },
  "saved_at_utc": "2026-02-28T06:41:00Z"
}