{
  "group.nd.name": "오마이걸 미미",
  "query": "(OH MY GIRL 미미 OR 미미 OH MY GIRL OR 미미 오마이걸 OR 오마이걸 미미) lang:ko -is:retweet -is:nullcast",
  "collab_start_week": "2024-W34",
  "collab_start_date": "2024-08-19",
  "window_start": "2024-02-19T00:00:00Z",
  "window_end": "2024-06-19T00:00:00Z",
  "weekly_counts": {
    "2024-W20": 39,
    "2024-W21": 59,
    "2024-W22": 44,
    "2024-W23": 50,
    "2024-W24": 33,
    "2024-W25": 11,
    "2024-W16": 44,
    "2024-W17": 45,
    "2024-W18": 54,
    "2024-W19": 53,
    "2024-W12": 49,
    "2024-W13": 59,
    "2024-W14": 44,
    "2024-W15": 36,
    "2024-W08": 56,
    "2024-W09": 45,
    "2024-W10": 44,
    "2024-W11": 33
  },
  "lag_features": {
    "count_lag_9w": 11,
    "count_lag_10w": 33,
    "count_lag_11w": 50,
    "count_lag_12w": 44,
    "count_lag_13w": 59,
    "count_lag_14w": 39,
    "count_lag_15w": 53,
    "count_lag_16w": 54,
    "count_lag_17w": 45,
    "count_lag_18w": 44,
    "count_lag_19w": 36,
    "count_lag_20w": 44,
    "count_lag_21w": 59,
    "count_lag_22w": 49,
    "count_lag_23w": 33,
    "count_lag_24w": 44,
    "count_lag_25w": 45,
    "count_lag_26w": 56
  },
  "total_count_2to6m": 798,
  "rate_limit": {
    "limit": "300",
    "remaining": "15",
    "reset": "1772287727"
  },
  "saved_at_utc": "2026-02-28T13:59:04Z"
}