{
  "group.nd.name": "위치스 마고",
  "query": "(WITCHX 마고 OR 마고 WITCHX OR 마고 위치스 OR 위치스 마고) lang:ko -is:retweet -is:nullcast",
  "collab_start_week": "2025-W50",
  "collab_start_date": "2025-12-08",
  "window_start": "2025-06-08T00:00:00Z",
  "window_end": "2025-10-08T00:00:00Z",
  "weekly_counts": {
    "2025-W36": 1,
    "2025-W37": 12,
    "2025-W38": 8,
    "2025-W39": 5,
    "2025-W40": 6,
    "2025-W41": 3,
    "2025-W32": 6,
    "2025-W33": 4,
    "2025-W34": 9,
    "2025-W35": 0,
    "2025-W28": 12,
    "2025-W29": 1,
    "2025-W30": 12,
    "2025-W31": 2,
    "2025-W23": 0,
    "2025-W24": 12,
    "2025-W25": 3,
    "2025-W26": 18,
    "2025-W27": 2
  },
  "lag_features": {
    "count_lag_9w": 3,
    "count_lag_10w": 6,
    "count_lag_11w": 5,
    "count_lag_12w": 8,
    "count_lag_13w": 12,
    "count_lag_14w": 1,
    "count_lag_15w": 0,
    "count_lag_16w": 9,
    "count_lag_17w": 4,
    "count_lag_18w": 6,
    "count_lag_19w": 2,
    "count_lag_20w": 12,
    "count_lag_21w": 1,
    "count_lag_22w": 12,
    "count_lag_23w": 2,
    "count_lag_24w": 18,
    "count_lag_25w": 3,
    "count_lag_26w": 12
  },
  "total_count_2to6m": 116,
  "rate_limit": {
    "limit": "300",
    "remaining": "184",
    "reset": "1772293016"
  },
  "saved_at_utc": "2026-02-28T15:23:35Z"
}