{
  "group.nd.name": "이븐 박지훈",
  "query": "(EVNNE 박지훈 OR 박지훈 EVNNE OR 박지훈 이븐 OR 이븐 박지훈) lang:ko -is:retweet -is:nullcast",
  "collab_start_week": "2024-W03",
  "collab_start_date": "2024-01-15",
  "window_start": "2023-07-15T00:00:00Z",
  "window_end": "2023-11-15T00:00:00Z",
  "weekly_counts": {
    "2023-W41": 2,
    "2023-W42": 4,
    "2023-W43": 0,
    "2023-W44": 0,
    "2023-W45": 1,
    "2023-W46": 0,
    "2023-W37": 0,
    "2023-W38": 0,
    "2023-W39": 0,
    "2023-W40": 2,
    "2023-W33": 0,
    "2023-W34": 0,
    "2023-W35": 0,
    "2023-W36": 0,
    "2023-W28": 0,
    "2023-W29": 0,
    "2023-W30": 0,
    "2023-W31": 0,
    "2023-W32": 0
  },
  "lag_features": {
    "count_lag_9w": 0,
    "count_lag_10w": 1,
    "count_lag_11w": 0,
    "count_lag_12w": 0,
    "count_lag_13w": 4,
    "count_lag_14w": 2,
    "count_lag_15w": 2,
    "count_lag_16w": 0,
    "count_lag_17w": 0,
    "count_lag_18w": 0,
    "count_lag_19w": 0,
    "count_lag_20w": 0,
    "count_lag_21w": 0,
    "count_lag_22w": 0,
    "count_lag_23w": 0,
    "count_lag_24w": 0,
    "count_lag_25w": 0,
    "count_lag_26w": 0
  },
  "total_count_2to6m": 9,
  "rate_limit": {
    "limit": "300",
    "remaining": "48",
    "reset": "1772294166"
  },
  "saved_at_utc": "2026-02-28T15:45:04Z"
}