{
  "group.nd.name": "이븐 박지후",
  "query": "(EVNNE 박지후 OR 박지후 EVNNE OR 박지후 이븐 OR 이븐 박지후) lang:ko -is:retweet -is:nullcast",
  "collab_start_week": "2025-W31",
  "collab_start_date": "2025-07-28",
  "window_start": "2025-01-28T00:00:00Z",
  "window_end": "2025-05-28T00:00:00Z",
  "weekly_counts": {
    "2025-W17": 63,
    "2025-W18": 50,
    "2025-W19": 79,
    "2025-W20": 57,
    "2025-W21": 96,
    "2025-W22": 16,
    "2025-W13": 102,
    "2025-W14": 104,
    "2025-W15": 68,
    "2025-W16": 77,
    "2025-W09": 88,
    "2025-W10": 89,
    "2025-W11": 81,
    "2025-W12": 85,
    "2025-W05": 89,
    "2025-W06": 56,
    "2025-W07": 270,
    "2025-W08": 240
  },
  "lag_features": {
    "count_lag_9w": 16,
    "count_lag_10w": 96,
    "count_lag_11w": 57,
    "count_lag_12w": 79,
    "count_lag_13w": 50,
    "count_lag_14w": 63,
    "count_lag_15w": 77,
    "count_lag_16w": 68,
    "count_lag_17w": 104,
    "count_lag_18w": 102,
    "count_lag_19w": 85,
    "count_lag_20w": 81,
    "count_lag_21w": 89,
    "count_lag_22w": 88,
    "count_lag_23w": 240,
    "count_lag_24w": 270,
    "count_lag_25w": 56,
    "count_lag_26w": 89
  },
  "total_count_2to6m": 1710,
  "rate_limit": {
    "limit": "300",
    "remaining": "52",
    "reset": "1772294166"
  },
  "saved_at_utc": "2026-02-28T15:45:01Z"
}