{
  "group.nd.name": "태호",
  "query": "태호 lang:ko -is:retweet -is:nullcast",
  "collab_start_week": "2025-W37",
  "collab_start_date": "2025-09-08",
  "window_start": "2025-03-08T00:00:00Z",
  "window_end": "2025-07-08T00:00:00Z",
  "weekly_counts": {
    "2025-W23": 103,
    "2025-W24": 118,
    "2025-W25": 111,
    "2025-W26": 126,
    "2025-W27": 83,
    "2025-W28": 19,
    "2025-W19": 138,
    "2025-W20": 153,
    "2025-W21": 159,
    "2025-W22": 163,
    "2025-W14": 96,
    "2025-W15": 130,
    "2025-W16": 174,
    "2025-W17": 169,
    "2025-W18": 168,
    "2025-W10": 55,
    "2025-W11": 171,
    "2025-W12": 141,
    "2025-W13": 149
  },
  "lag_features": {
    "count_lag_9w": 19,
    "count_lag_10w": 83,
    "count_lag_11w": 126,
    "count_lag_12w": 111,
    "count_lag_13w": 118,
    "count_lag_14w": 103,
    "count_lag_15w": 163,
    "count_lag_16w": 159,
    "count_lag_17w": 153,
    "count_lag_18w": 138,
    "count_lag_19w": 168,
    "count_lag_20w": 169,
    "count_lag_21w": 174,
    "count_lag_22w": 130,
    "count_lag_23w": 96,
    "count_lag_24w": 149,
    "count_lag_25w": 141,
    "count_lag_26w": 171
  },
  "total_count_2to6m": 2371,
  "rate_limit": {
    "limit": "300",
    "remaining": "40",
    "reset": "1772319540"
  },
  "saved_at_utc": "2026-02-28T22:48:05Z"
}