{
  "group.nd.name": "하이키 휘서",
  "query": "(\"H4-KEY 휘서\" OR 하이키 휘서 OR \"휘서 H4-KEY\" OR 휘서 하이키) lang:ko -is:retweet -is:nullcast",
  "collab_start_week": "2024-W24",
  "collab_start_date": "2024-06-10",
  "window_start": "2023-12-10T00:00:00Z",
  "window_end": "2024-04-10T00:00:00Z",
  "weekly_counts": {
    "2024-W10": 44,
    "2024-W11": 33,
    "2024-W12": 28,
    "2024-W13": 27,
    "2024-W14": 22,
    "2024-W15": 6,
    "2024-W06": 45,
    "2024-W07": 51,
    "2024-W08": 30,
    "2024-W09": 47,
    "2024-W02": 40,
    "2024-W03": 61,
    "2024-W04": 73,
    "2024-W05": 37,
    "2023-W49": 5,
    "2023-W50": 48,
    "2023-W51": 28,
    "2023-W52": 31,
    "2024-W01": 43
  },
  "lag_features": {
    "count_lag_9w": 6,
    "count_lag_10w": 22,
    "count_lag_11w": 27,
    "count_lag_12w": 28,
    "count_lag_13w": 33,
    "count_lag_14w": 44,
    "count_lag_15w": 47,
    "count_lag_16w": 30,
    "count_lag_17w": 51,
    "count_lag_18w": 45,
    "count_lag_19w": 37,
    "count_lag_20w": 73,
    "count_lag_21w": 61,
    "count_lag_22w": 40,
    "count_lag_23w": 43,
    "count_lag_24w": 31,
    "count_lag_25w": 28,
    "count_lag_26w": 48
  },
  "total_count_2to6m": 694,
  "rate_limit": {
    "limit": "300",
    "remaining": "260",
    "reset": "1772451908"
  },
  "saved_at_utc": "2026-03-02T11:30:50Z"
}